{"nodes": [{"id": "reports_routes", "label": "reports.routes", "file_type": "code", "source_file": "backend/routes/reports.routes.js", "source_location": null, "source_url": null, "captured_at": null, "author": null, "contributor": null}, {"id": "reports_routes", "label": "reports.routes.js", "file_type": "code", "source_file": "backend/routes/reports.routes.js", "source_location": null, "source_url": null, "captured_at": null, "author": null, "contributor": null}], "edges": [{"source": "reports_routes", "target": "report_service", "relation": "calls", "confidence": "EXTRACTED", "confidence_score": 1.0, "source_file": "backend/routes/reports.routes.js", "source_location": "line 4-6 via generateReport controller", "weight": 1.0}], "hyperedges": []}